mcp_jupyter_notebook/__init__.py
mcp_jupyter_notebook/server.py
mcp_jupyter_notebook/tools/__init__.py
mcp_jupyter_notebook/tools/notebook.py
mcp_jupyter_notebook/tools/postgresql.py
mcp_jupyter_notebook-0.1.9.dist-info/licenses/LICENSE
mcp_jupyter_notebook-0.1.9.dist-info/METADATA
mcp_jupyter_notebook-0.1.9.dist-info/WHEEL
mcp_jupyter_notebook-0.1.9.dist-info/entry_points.txt
mcp_jupyter_notebook-0.1.9.dist-info/top_level.txt
mcp_jupyter_notebook-0.1.9.dist-info/RECORD
