Metadata-Version: 2.4
Name: mcp-jupyter-notebook
Version: 0.1.9
Summary: A MCP server for AI agents to interact with a Jupyter server
Author-email: Roberto Rodriguez <9653181+Cyb3rWard0g@users.noreply.github.com>
Requires-Python: >=3.13
License-File: LICENSE
Requires-Dist: fastmcp>=2.11.3
Requires-Dist: ipykernel>=6.30.1
Requires-Dist: ipywidgets>=8.1.7
Requires-Dist: jupyter-agent-toolkit>=0.1.9
Requires-Dist: mcp>=1.12.4
Requires-Dist: starlette>=0.47.2
Requires-Dist: uvicorn>=0.35.0
Provides-Extra: dev
Requires-Dist: pytest>=8.4.2; extra == "dev"
Requires-Dist: pytest-asyncio>=0.23; extra == "dev"
Requires-Dist: ruff; extra == "dev"
Requires-Dist: flake8; extra == "dev"
Requires-Dist: black; extra == "dev"
Requires-Dist: fastmcp; extra == "dev"
Requires-Dist: mcp; extra == "dev"
Requires-Dist: jupyter-agent-toolkit; extra == "dev"
Requires-Dist: anyio>=4; extra == "dev"
Requires-Dist: ipykernel; extra == "dev"
Requires-Dist: build; extra == "dev"
Requires-Dist: twine; extra == "dev"
Requires-Dist: packaging; extra == "dev"
Requires-Dist: setuptools; extra == "dev"
Requires-Dist: setuptools_scm; extra == "dev"
Requires-Dist: wheel; extra == "dev"
Dynamic: license-file
